LICENSE
README.md
setup.cfg
setup.py
bin/mympirun.py
bin/mympisanity.py
bin/mypmirun.py
bin/mytaskprolog.py
bin/mytasks.py
bin/pbsssh.sh
bin/sshsleep.sh
lib/vsc/__init__.py
lib/vsc/mympirun/__init__.py
lib/vsc/mympirun/common.py
lib/vsc/mympirun/factory.py
lib/vsc/mympirun/main.py
lib/vsc/mympirun/option.py
lib/vsc/mympirun/mpi/__init__.py
lib/vsc/mympirun/mpi/intelmpi.py
lib/vsc/mympirun/mpi/mpi.py
lib/vsc/mympirun/mpi/mpich.py
lib/vsc/mympirun/mpi/openmpi.py
lib/vsc/mympirun/mpi/option.py
lib/vsc/mympirun/pmi/__init__.py
lib/vsc/mympirun/pmi/mpi.py
lib/vsc/mympirun/pmi/option.py
lib/vsc/mympirun/pmi/pmi.py
lib/vsc/mympirun/pmi/sched.py
lib/vsc/mympirun/pmi/slurm.py
lib/vsc/mympirun/rm/__init__.py
lib/vsc/mympirun/rm/local.py
lib/vsc/mympirun/rm/pbs.py
lib/vsc/mympirun/rm/sched.py
lib/vsc/mympirun/rm/scoop.py
lib/vsc/mympirun/rm/slurm.py
lib/vsc_mympirun.egg-info/PKG-INFO
lib/vsc_mympirun.egg-info/SOURCES.txt
lib/vsc_mympirun.egg-info/dependency_links.txt
lib/vsc_mympirun.egg-info/namespace_packages.txt
lib/vsc_mympirun.egg-info/not-zip-safe
lib/vsc_mympirun.egg-info/requires.txt
lib/vsc_mympirun.egg-info/top_level.txt