Metadata-Version: 2.1
Name: vsc-mympirun
Version: 5.5.0
Summary: `mympirun` is a tool to make it easier for users of HPC clusters to run MPI programs with good performance.
Home-page: https://github.com/hpcugent/vsc-mympirun
Download-URL: 
Author: Stijn De Weirdt;Kenneth Hoste
Author-email: stijn.deweirdt@ugent.be, kenneth.hoste@ugent.be
Maintainer: Stijn De Weirdt;Kenneth Hoste
Maintainer-email: stijn.deweirdt@ugent.be, kenneth.hoste@ugent.be
License: GPLv2
Classifier: License :: OSI Approved :: GNU General Public License v2 (GPLv2)
License-File: LICENSE
Requires-Dist: vsc-base>=3.5.3
Requires-Dist: vsc-install>=0.15.1
Requires-Dist: IPy
